rbStata
tests
