Metadata-Version: 2.1
Name: rbstata
Version: 0.1.1
Summary: A command-line utility that converts (or roll back) versions of Stata dta data files.
Home-page: https://github.com/lsys/rbStata
Author: Lucas Shen
Author-email: lucas@lucasshen.com
License: MIT
Keywords: Stata,Python,cli,compatibility,version
Classifier: Environment :: Console
Classifier: Intended Audience :: Developers
Classifier: Natural Language :: English
Classifier: License :: OSI Approved :: MIT License
Classifier: Programming Language :: Python :: 3 :: Only
Classifier: Programming Language :: Python :: 3
Classifier: Programming Language :: Python :: 3.7
Classifier: Programming Language :: Python :: 3.8
Classifier: Programming Language :: Python :: 3.9
Classifier: Programming Language :: Python :: 3.10
Classifier: Programming Language :: Python
Classifier: Topic :: Software Development
Requires-Python: >=3.7
License-File: LICENSE
